ddrclass.py
ddrfactlib.py
ddrparserlib.py
ddrrun.py
genie_parsers.py
ddr_clips-1.1.15.dist-info/METADATA
ddr_clips-1.1.15.dist-info/WHEEL
ddr_clips-1.1.15.dist-info/top_level.txt
ddr_clips-1.1.15.dist-info/RECORD
