Metadata-Version: 2.1
Name: ddr-clips
Version: 1.1.15
Summary: Distributed Device Reasoning (DDR) CLIPs runtime
Home-page: https://wwwin-github.cisco.com/petervh/ddr-clips
Author: Peter Van Horne
Author-email: petervh@cisco.com
Classifier: Programming Language :: Python :: 3
Classifier: License :: OSI Approved :: MIT License
Classifier: Operating System :: OS Independent
Requires-Python: >=3.6
